usergen/__init__.py
usergen/__main__.py
usergen/parsers.py
usergen-0.1.3.dist-info/WHEEL
usergen-0.1.3.dist-info/METADATA
usergen-0.1.3.dist-info/RECORD
