Metadata-Version: 2.1
Name: usergen
Version: 0.1.3
Summary: A simple cli package to make requests on randomuser api.
Author: João Nogueira
Author-email: joaopcnogueira@gmail.com
Requires-Python: >=3.8,<4.0
Classifier: Programming Language :: Python :: 3
Classifier: Programming Language :: Python :: 3.10
Classifier: Programming Language :: Python :: 3.8
Classifier: Programming Language :: Python :: 3.9
Requires-Dist: pandas (>=1.4.2,<2.0.0)
Requires-Dist: requests (>=2.27.1,<3.0.0)
